ttg/__init__.py
ttg/ttg.py
ttg/ttg_cli.py
ttg/tests/__init__.py
ttg/tests/test_ttg.py
ttg/tests/test_ttg_cli.py
ttg/tools/__init__.py
ttg/tools/evaluation.py
ttg/tools/parsing.py
truth_table_generator-2.0.0.dist-info/LICENSE
truth_table_generator-2.0.0.dist-info/METADATA
truth_table_generator-2.0.0.dist-info/WHEEL
truth_table_generator-2.0.0.dist-info/entry_points.txt
truth_table_generator-2.0.0.dist-info/top_level.txt
truth_table_generator-2.0.0.dist-info/RECORD
