Metadata-Version: 2.1
Name: truth-table-generator
Version: 2.0.0
Summary: Python API that auto generates truth tables
Home-page: https://github.com/chicolucio/truth-table-generator
Author: Francisco Bustamante
Author-email: chicolucio@gmail.com
License: Apache Software License
Keywords: truth,table,truth table,truthtable,generator,logic,tautology,ttg
Classifier: Development Status :: 5 - Production/Stable
Classifier: Environment :: Console
Classifier: Intended Audience :: Science/Research
Classifier: License :: OSI Approved :: Apache Software License
Classifier: Natural Language :: English
Classifier: Programming Language :: Python
Classifier: Programming Language :: Python :: 3
Classifier: Topic :: Scientific/Engineering :: Mathematics
Requires-Python: >=3.10
License-File: LICENSE
Requires-Dist: numpy
Requires-Dist: pandas
Requires-Dist: PTable
Requires-Dist: pyparsing
Requires-Dist: tabulate
Requires-Dist: jinja2
